{
    "reign_start": [
        "PopulatedPlace"
    ], 
    "index": [
        "PopulatedPlace", 
        "Person"
    ], 
    "verif_who": [
        "PopulatedPlace", 
        "Person"
    ], 
    "death": [
        "PopulatedPlace"
    ], 
    "name": [
        "PopulatedPlace"
    ], 
    "cause": [
        "PopulatedPlace", 
        "Person"
    ], 
    "notes": [
        "PopulatedPlace", 
        "Person"
    ], 
    "rise": [
        "PopulatedPlace", 
        "Person"
    ], 
    "dynasty": [
        "PopulatedPlace"
    ], 
    "birth_prv": [
        "PopulatedPlace"
    ], 
    "reign_end": [
        "PopulatedPlace"
    ], 
    "era": [
        "PopulatedPlace"
    ], 
    "birth": [
        "PopulatedPlace"
    ], 
    "image": [
        "PopulatedPlace"
    ], 
    "name_full": [
        "PopulatedPlace"
    ], 
    "birth_cty": [
        "PopulatedPlace"
    ]
}